Metadata-Version: 2.1
Name: chorde
Version: 1.0.8
Summary: Clustered Caching Library
Home-page: https://github.com/klaussfreire/chorde
Author: Claudio Freire
Author-email: klaussfreire@gmail.com
License: LGPLv3
Classifier: Development Status :: 4 - Beta
Classifier: Intended Audience :: Developers
Classifier: License :: OSI Approved :: GNU Lesser General Public License v3 (LGPLv3)
Classifier: Programming Language :: Python
Classifier: Programming Language :: Cython
Classifier: Programming Language :: Python :: 3
Classifier: Topic :: Software Development :: Libraries
Classifier: Operating System :: OS Independent
Requires-Python: >=3.6
Provides-Extra: shmem
Provides-Extra: mq
Provides-Extra: memcache
Provides-Extra: elasticache
